{"name":"vue","slug":"vue","count":1,"postlist":[{"title":"打包vue组件为依赖(踩坑记录)","uid":"e8914152cbd2f8ddb44af0ed03340963","slug":"打包vue组件","date":"2023-11-01T08:42:32.815Z","updated":"2023-11-01T10:07:21.205Z","comments":true,"path":"api/articles/打包vue组件.json","keywords":null,"cover":[],"text":"这篇主要是记录一下将vue的一个组件,打包成可以npm安装的依赖的过程中,遇到的问题和一些理解 背景: 有这个想法是因为有一个对比admin管理系统来说非常常见的一个组件(搜索+表格的组件),希望能打包成依赖在不同的项目中方便随时引用而不是复制代码 组件内部实现逻辑先不论 使用的...","link":"","photos":[],"count_time":{"symbolsCount":"3.6k","symbolsTime":"3 mins."},"categories":[{"name":"vue","slug":"vue","count":1,"path":"api/categories/vue.json"}],"tags":[{"name":"vue","slug":"vue","count":1,"path":"api/tags/vue.json"}],"author":{"name":"xm","slug":"blog-author","avatar":"/img/avatar.jpg","link":"/","description":"","socials":{"github":"","twitter":"","stackoverflow":"","wechat":"","qq":"","weibo":"","zhihu":"","csdn":"","juejin":"","customs":{}}},"feature":true}]}